{"nodes": [{"id": "student_src_utils_languagetool_js", "label": "languagetool.js", "file_type": "code", "source_file": "student/src/utils/languagetool.js", "source_location": "L1"}, {"id": "languagetool_ltdisable", "label": "LTdisable()", "file_type": "code", "source_file": "student/src/utils/languagetool.js", "source_location": "L25"}, {"id": "languagetool_ltcheckallwords", "label": "LTcheckAllWords()", "file_type": "code", "source_file": "student/src/utils/languagetool.js", "source_location": "L55"}, {"id": "languagetool_ltignoreword", "label": "LTignoreWord()", "file_type": "code", "source_file": "student/src/utils/languagetool.js", "source_location": "L168"}, {"id": "languagetool_ltresetignorelist", "label": "LTresetIgnorelist()", "file_type": "code", "source_file": "student/src/utils/languagetool.js", "source_location": "L172"}, {"id": "languagetool_lthandlemisspelled", "label": "LThandleMisspelled()", "file_type": "code", "source_file": "student/src/utils/languagetool.js", "source_location": "L176"}, {"id": "languagetool_ltfindwordpositions", "label": "LTfindWordPositions()", "file_type": "code", "source_file": "student/src/utils/languagetool.js", "source_location": "L202"}, {"id": "languagetool_ltbuildoffsetmap", "label": "LTbuildOffsetMap()", "file_type": "code", "source_file": "student/src/utils/languagetool.js", "source_location": "L408"}, {"id": "languagetool_ltfindbyoffsetmap", "label": "LTfindByOffsetMap()", "file_type": "code", "source_file": "student/src/utils/languagetool.js", "source_location": "L437"}, {"id": "languagetool_lthighlightwords", "label": "LThighlightWords()", "file_type": "code", "source_file": "student/src/utils/languagetool.js", "source_location": "L514"}, {"id": "languagetool_ltredrawhighlights", "label": "LTredrawHighlights()", "file_type": "code", "source_file": "student/src/utils/languagetool.js", "source_location": "L576"}], "edges": [{"source": "student_src_utils_languagetool_js", "target": "student_src_utils_signalbridge_ts", "relation": "imports_from", "confidence": "EXTRACTED", "source_file": "student/src/utils/languagetool.js", "source_location": "L18", "weight": 1.0}, {"source": "student_src_utils_languagetool_js", "target": "languagetool_ltdisable", "relation": "contains", "confidence": "EXTRACTED", "source_file": "student/src/utils/languagetool.js", "source_location": "L25", "weight": 1.0}, {"source": "student_src_utils_languagetool_js", "target": "languagetool_ltcheckallwords", "relation": "contains", "confidence": "EXTRACTED", "source_file": "student/src/utils/languagetool.js", "source_location": "L55", "weight": 1.0}, {"source": "student_src_utils_languagetool_js", "target": "languagetool_ltignoreword", "relation": "contains", "confidence": "EXTRACTED", "source_file": "student/src/utils/languagetool.js", "source_location": "L168", "weight": 1.0}, {"source": "student_src_utils_languagetool_js", "target": "languagetool_ltresetignorelist", "relation": "contains", "confidence": "EXTRACTED", "source_file": "student/src/utils/languagetool.js", "source_location": "L172", "weight": 1.0}, {"source": "student_src_utils_languagetool_js", "target": "languagetool_lthandlemisspelled", "relation": "contains", "confidence": "EXTRACTED", "source_file": "student/src/utils/languagetool.js", "source_location": "L176", "weight": 1.0}, {"source": "student_src_utils_languagetool_js", "target": "languagetool_ltfindwordpositions", "relation": "contains", "confidence": "EXTRACTED", "source_file": "student/src/utils/languagetool.js", "source_location": "L202", "weight": 1.0}, {"source": "student_src_utils_languagetool_js", "target": "languagetool_ltbuildoffsetmap", "relation": "contains", "confidence": "EXTRACTED", "source_file": "student/src/utils/languagetool.js", "source_location": "L408", "weight": 1.0}, {"source": "student_src_utils_languagetool_js", "target": "languagetool_ltfindbyoffsetmap", "relation": "contains", "confidence": "EXTRACTED", "source_file": "student/src/utils/languagetool.js", "source_location": "L437", "weight": 1.0}, {"source": "student_src_utils_languagetool_js", "target": "languagetool_lthighlightwords", "relation": "contains", "confidence": "EXTRACTED", "source_file": "student/src/utils/languagetool.js", "source_location": "L514", "weight": 1.0}, {"source": "student_src_utils_languagetool_js", "target": "languagetool_ltredrawhighlights", "relation": "contains", "confidence": "EXTRACTED", "source_file": "student/src/utils/languagetool.js", "source_location": "L576", "weight": 1.0}, {"source": "languagetool_ltcheckallwords", "target": "languagetool_ltdisable", "relation": "calls", "confidence": "EXTRACTED", "source_file": "student/src/utils/languagetool.js", "source_location": "L68", "weight": 1.0}, {"source": "languagetool_ltcheckallwords", "target": "languagetool_lthandlemisspelled", "relation": "calls", "confidence": "EXTRACTED", "source_file": "student/src/utils/languagetool.js", "source_location": "L143", "weight": 1.0}, {"source": "languagetool_ltfindwordpositions", "target": "languagetool_ltbuildoffsetmap", "relation": "calls", "confidence": "EXTRACTED", "source_file": "student/src/utils/languagetool.js", "source_location": "L383", "weight": 1.0}, {"source": "languagetool_lthighlightwords", "target": "languagetool_ltdisable", "relation": "calls", "confidence": "EXTRACTED", "source_file": "student/src/utils/languagetool.js", "source_location": "L517", "weight": 1.0}, {"source": "languagetool_ltredrawhighlights", "target": "languagetool_lthighlightwords", "relation": "calls", "confidence": "EXTRACTED", "source_file": "student/src/utils/languagetool.js", "source_location": "L590", "weight": 1.0}]}